oasis/__init__.py
oasis/functions.py
oasis/oasis_methods.cpython-313-darwin.so
oasis/plotting.py
oasis_deconv-0.2.1.dist-info/LICENSE
oasis_deconv-0.2.1.dist-info/METADATA
oasis_deconv-0.2.1.dist-info/WHEEL
oasis_deconv-0.2.1.dist-info/top_level.txt
oasis_deconv-0.2.1.dist-info/RECORD
