Metadata-Version: 2.2
Name: oasis-deconv
Version: 0.2.1
Summary: Fast algorithm for deconvolution of neural calcium imaging traces
Home-page: https://github.com/j-friedrich/OASIS
Author: Johannes Friedrich
Author-email: johannes.friedrich@alleninstitute.org
License: GPL-3
License-File: LICENSE
Requires-Dist: numpy
Requires-Dist: scipy
Requires-Dist: matplotlib
Requires-Dist: Cython
Dynamic: author
Dynamic: author-email
Dynamic: description
Dynamic: description-content-type
Dynamic: home-page
Dynamic: license
Dynamic: requires-dist
Dynamic: summary
